anitracker/__init__.py
anitracker/__main__.py
anitracker/anitracker.py
anitracker/background.py
anitracker/config.py
anitracker/resources_rc.py
anitracker/gql/__init__.py
anitracker/gql/queries.py
anitracker/media/__init__.py
anitracker/media/anime.py
anitracker/sync/__init__.py
anitracker/sync/anilist.py
anitracker/ui/__init__.py
anitracker/ui/about.py
anitracker/ui/anime_info.py
anitracker/ui/app.py
anitracker/ui/settings.py
anitracker-0.2.1.dist-info/LICENSE
anitracker-0.2.1.dist-info/METADATA
anitracker-0.2.1.dist-info/WHEEL
anitracker-0.2.1.dist-info/entry_points.txt
anitracker-0.2.1.dist-info/top_level.txt
anitracker-0.2.1.dist-info/RECORD
