Metadata-Version: 2.1
Name: anitracker
Version: 0.2.1
Summary: A tool used to help track, play, and sync anime episodes with services such as anilist
Home-page: https://github.com/Phxntxm/AniTracker
Author: Dan Hess
Author-email: phxntxm1@gmail.com
License: UNKNOWN
Project-URL: Bug Tracker, https://github.com/Phxntxm/AniTracker
Platform: UNKNOWN
Classifier: Programming Language :: Python :: 3
Classifier: License :: OSI Approved :: MIT License
Requires-Python: >=3.8
License-File: LICENSE
Requires-Dist: ffmpeg-python
Requires-Dist: anitopy
Requires-Dist: fuzzywuzzy[speedup]
Requires-Dist: toml
Requires-Dist: PySide6
Requires-Dist: requests
